defi_assessment/__init__.py
defi_assessment/cli.py
defi_assessment/run.py
defi_assessment/app/__init__.py
defi_assessment/app/data.py
defi_assessment/app/suggest.py
defi_assessment/app/templates/form.html
defi_assessment/app/templates/graph.html
defi_assessment/app/templates/index.html
defi_assessment/data_collection/__init__.py
defi_assessment/data_collection/contract.py
defi_assessment/data_collection/finance.py
defi_assessment/git_tool/__init__.py
defi_assessment/git_tool/gitcmd.py
defi_assessment/git_tool/parser.py
defi_assessment/modelling/__init__.py
defi_assessment/modelling/contract.py
defi_assessment/modelling/finance.py
defi_assessment/preprocess/__init__.py
defi_assessment/preprocess/contract.py
DeFi_Assessment-0.2.3.dev1.dist-info/LICENSE
DeFi_Assessment-0.2.3.dev1.dist-info/METADATA
DeFi_Assessment-0.2.3.dev1.dist-info/WHEEL
DeFi_Assessment-0.2.3.dev1.dist-info/entry_points.txt
DeFi_Assessment-0.2.3.dev1.dist-info/top_level.txt
DeFi_Assessment-0.2.3.dev1.dist-info/RECORD
