Metadata-Version: 2.1
Name: DeFi-Assessment
Version: 0.2.3.dev1
Summary: A prototype project to perfrom risk assessment for DeFi lending platforms.
Home-page: UNKNOWN
Author: CHEN Da
Author-email: chendamailbox@foxmail.com
License: UNKNOWN
Project-URL: Source, https://github.com/yuukidach/DeFi-Assessment
Platform: UNKNOWN
License-File: LICENSE
Requires-Dist: Flask (>=1.1.2)
Requires-Dist: requests (>=2.26.0)
Requires-Dist: imbalanced-learn (>=0.8.1)
Requires-Dist: matplotlib (>=3.4.3)
Requires-Dist: pandas (>=1.3.4)
Requires-Dist: loguru (>=0.5.3)
Requires-Dist: joblib (>=1.1.0)
Requires-Dist: plotly (>=5.3.1)
Requires-Dist: WTForms (~=2.3.3)
Requires-Dist: textblob (>=0.15.3)
Requires-Dist: tqdm (~=4.62.3)
Requires-Dist: beautifulsoup4
Requires-Dist: scikit-learn (>=1.0.1)
Provides-Extra: cpu
Requires-Dist: tensorflow (<=2.5.0,>=2.4.0) ; extra == 'cpu'
Provides-Extra: gpu
Requires-Dist: tensorflow-gpu (<=2.5.0,>=2.4.0) ; extra == 'gpu'
